[
  {
    "fixture_id": 537333,
    "fotmob_match_id": 4667757,
    "team_name": "Canada",
    "opponent_name": "Bosnia-Herzegovina",
    "goals_for": 1.0,
    "goals_against": 1.0,
    "shots": null,
    "shots_on_target": 4,
    "expected_goals": null,
    "possession": null,
    "passes": 421,
    "pass_accuracy": null,
    "corners": 9,
    "fouls": null,
    "yellow_cards": 2,
    "red_cards": 0,
    "big_chances": 2,
    "big_chances_missed": 2,
    "saves": null,
    "tackles": 23,
    "interceptions": 4,
    "clearances": 21
  },
  {
    "fixture_id": 537333,
    "fotmob_match_id": 4667757,
    "team_name": "Bosnia-Herzegovina",
    "opponent_name": "Canada",
    "goals_for": 1.0,
    "goals_against": 1.0,
    "shots": null,
    "shots_on_target": 3,
    "expected_goals": null,
    "possession": null,
    "passes": 271,
    "pass_accuracy": null,
    "corners": 4,
    "fouls": null,
    "yellow_cards": 3,
    "red_cards": 0,
    "big_chances": 2,
    "big_chances_missed": 1,
    "saves": null,
    "tackles": 20,
    "interceptions": 11,
    "clearances": 70
  }
]